stacklogging/__init__.py
stacklogging/main.py
stacklogging-0.1.4.dist-info/LICENSE
stacklogging-0.1.4.dist-info/METADATA
stacklogging-0.1.4.dist-info/WHEEL
stacklogging-0.1.4.dist-info/top_level.txt
stacklogging-0.1.4.dist-info/RECORD
