Metadata-Version: 2.1
Name: stacklogging
Version: 0.1.4
Summary: Python structured logging with Google Cloud Stackdriver API integration
Home-page: https://github.com/bufferapp/stacklogging
Author: David Gasquez
Author-email: davidgasquez@buffer.com
License: MIT
Keywords: stackdriver,logging,google-cloud
Platform: UNKNOWN
